{"stats":{"minecraft:custom":{"minecraft:jump":23,"minecraft:interact_with_brewingstand":1,"minecraft:time_since_rest":8962,"minecraft:damage_dealt":50,"minecraft:crouch_one_cm":112,"minecraft:leave_game":1,"minecraft:sprint_one_cm":62,"minecraft:play_time":8962,"minecraft:walk_on_water_one_cm":176,"minecraft:time_since_death":8962,"minecraft:walk_one_cm":18624,"minecraft:bell_ring":18,"minecraft:sneak_time":889,"minecraft:total_world_time":9221,"minecraft:walk_under_water_one_cm":971,"minecraft:talked_to_villager":1,"minecraft:fly_one_cm":143816,"minecraft:open_chest":2}},"DataVersion":3465}